haystack/__init__.py
haystack/cli.py
haystack/find_plus_context.py
haystack/run.py
haystack/types.py
haystack/assets/example.txt
search_haystack-1.0.3.dist-info/LICENSE
search_haystack-1.0.3.dist-info/METADATA
search_haystack-1.0.3.dist-info/WHEEL
search_haystack-1.0.3.dist-info/entry_points.txt
search_haystack-1.0.3.dist-info/top_level.txt
search_haystack-1.0.3.dist-info/RECORD
