Metadata-Version: 2.1
Name: search-haystack
Version: 1.0.3
Summary: searches through loads of files for simple searches that are next to each other, like clean, air
Home-page: https://github.com/zackees/haystack
Maintainer: Zachary Vorhies
License: BSD 3-Clause License
Keywords: template-python-cmd
Classifier: Programming Language :: Python :: 3
Requires-Python: >=3.7
License-File: LICENSE
